{
  "slug": "taxi-vodice-seget",
  "title": "Taxi Vodice - Seget | Pevná cena €110 | TAXI Antonio",
  "description": "Taxi a soukromý transfer, trasa Vodice - Seget. Pevná cena €110 za vozidlo, až 4 cestující, ode dveří ke dveřím. Rezervujte přímo u Antonia.",
  "keywords": "taxi vodice - seget, transfer vodice - seget, letištní transfer vodice - seget",
  "og_image": "https://taxisibenik.hr/assets/img/hero-transfers.webp",
  "schema": [
    {
      "@context": "https://schema.org",
      "@type": "Service",
      "serviceType": "Soukromý taxi transfer",
      "name": "Taxi Vodice - Seget",
      "description": "Taxi a soukromý transfer za pevnou cenu, trasa Vodice - Seget, 110 eur za vozidlo až pro 4 cestující, ode dveří ke dveřím.",
      "provider": {
        "@type": "LocalBusiness",
        "name": "Taxi Antonio",
        "telephone": "+385994471013",
        "email": "info@taxisibenik.hr",
        "address": {
          "@type": "PostalAddress",
          "addressLocality": "Šibenik",
          "addressCountry": "HR"
        },
        "aggregateRating": {
          "@type": "AggregateRating",
          "ratingValue": "4.9",
          "reviewCount": "152"
        }
      },
      "areaServed": [
        "Vodice",
        "Seget"
      ],
      "url": "https://taxisibenik.hr/cs/taxi-vodice-seget/",
      "offers": {
        "@type": "Offer",
        "price": "110",
        "priceCurrency": "EUR",
        "description": "Soukromá jednosměrná jízda, trasa Vodice - Seget, za vozidlo až pro 4 cestující. Zpáteční 220 eur."
      }
    },
    {
      "@context": "https://schema.org",
      "@type": "FAQPage",
      "mainEntity": [
        {
          "@type": "Question",
          "name": "Kolik stojí taxi na trase Vodice - Seget?",
          "acceptedAnswer": {
            "@type": "Answer",
            "text": "Pevně 110 za vozidlo až pro 4 cestující, jednosměrná, zavazadla v ceně. Zpáteční jízda je 220."
          }
        },
        {
          "@type": "Question",
          "name": "Kde mě vyzvednete?",
          "acceptedAnswer": {
            "@type": "Answer",
            "text": "U vaší přesné adresy, ať jde o dům, hotel nebo apartmán. Pošlete adresu při rezervaci a potvrdím místo setkání."
          }
        },
        {
          "@type": "Question",
          "name": "S jakým předstihem rezervovat?",
          "acceptedAnswer": {
            "@type": "Answer",
            "text": "Alespoň 2 hodiny předem, abych potvrdil vozidlo a čas vyzvednutí. Pro rychlou jízdu zavolejte nebo napište na WhatsApp."
          }
        }
      ]
    }
  ]
}