{
  "slug": "taxi-dubrovnik-murter",
  "title": "Taksi Dubrovnik - Murter | Fiksna cena €535 | TAXI Antonio",
  "description": "Privatni taksi i transfer, relacija Dubrovnik - Murter. Fiksno €535 po vozilu, do 4 putnika, od vrata do vrata. Rezervišite direktno kod Antonija.",
  "keywords": "taksi dubrovnik - murter, transfer dubrovnik - murter, prevoz dubrovnik - murter",
  "og_image": "https://taxisibenik.hr/assets/img/hero-transfers.webp",
  "schema": [
    {
      "@context": "https://schema.org",
      "@type": "Service",
      "serviceType": "Privatni taksi transfer",
      "name": "Taksi Dubrovnik - Murter",
      "description": "Privatni taksi i transfer po fiksnoj ceni, relacija Dubrovnik - Murter, 535 evra po vozilu za do 4 putnika, od vrata do vrata.",
      "provider": {
        "@type": "LocalBusiness",
        "name": "Taxi Antonio",
        "telephone": "+385994471013",
        "email": "info@taxisibenik.hr",
        "address": {
          "@type": "PostalAddress",
          "addressLocality": "Šibenik",
          "addressCountry": "HR"
        },
        "aggregateRating": {
          "@type": "AggregateRating",
          "ratingValue": "4.9",
          "reviewCount": "152"
        }
      },
      "areaServed": [
        "Dubrovnik",
        "Murter"
      ],
      "url": "https://taxisibenik.hr/sr/taxi-dubrovnik-murter/",
      "offers": {
        "@type": "Offer",
        "price": "535",
        "priceCurrency": "EUR",
        "description": "Jednosmerni privatni transfer, relacija Dubrovnik - Murter, po vozilu za do 4 putnika. Povratno 1070 evra."
      }
    },
    {
      "@context": "https://schema.org",
      "@type": "FAQPage",
      "mainEntity": [
        {
          "@type": "Question",
          "name": "Kolika je udaljenost i koliko traje vožnja?",
          "acceptedAnswer": {
            "@type": "Answer",
            "text": "Vožnja na relaciji Dubrovnik - Murter duga je oko 322 km i traje otprilike 4 h 20 min u uobičajenom saobraćaju, nešto duže u letnjim gužvama. Polazak planiram tako da vas usporeni deo nikad ne požuri."
          }
        },
        {
          "@type": "Question",
          "name": "Koliko košta taksi na relaciji Dubrovnik - Murter?",
          "acceptedAnswer": {
            "@type": "Answer",
            "text": "Fiksno 535 po vozilu za do 4 putnika, jedan smer, s putarinama, gorivom i prtljagom. Povratna vožnja je 1070."
          }
        },
        {
          "@type": "Question",
          "name": "Da li je transfer privatan ili deljen?",
          "acceptedAnswer": {
            "@type": "Answer",
            "text": "Svaki je transfer privatan i od vrata do vrata, u Škodi Superb. Bez deljenja vozila i bez dodatnih zaustavljanja osim ako ih zatražite."
          }
        },
        {
          "@type": "Question",
          "name": "Možete li da stanete usput?",
          "acceptedAnswer": {
            "@type": "Answer",
            "text": "Da. Na dužim rutama rado stanem za kafu, fotografiju ili kratku znamenitost. Samo javite pri rezervaciji."
          }
        },
        {
          "@type": "Question",
          "name": "Koliko unapred treba da rezervišem?",
          "acceptedAnswer": {
            "@type": "Answer",
            "text": "Barem 2 sata unapred da potvrdim vozilo i vreme preuzimanja. Za brži termin pozovite ili pišite na WhatsApp."
          }
        }
      ]
    }
  ]
}