{
  "slug": "bellevue-transfer",
  "title": "Bellevue Superior Hotel transfery Šibenik | Pevné ceny | TAXI Antonio",
  "description": "Soukromé transfery do a z Bellevue Superior Hotel v Šibeniku. Pevné ceny při rezervaci předem: letiště Split €95, letiště Zadar €130, Krka od €45. Ode dveří ke dveřím, jeden místní řidič.",
  "keywords": "bellevue šibenik transfery, bellevue superior hotel transfer, bellevue šibenik taxi, bellevue transfer na letiště, taxi bellevue šibenik",
  "og_image": "https://taxisibenik.hr/assets/img/hero-transfers.webp",
  "schema": [
    {
      "@context": "https://schema.org",
      "@type": "Service",
      "serviceType": "Hotelové transfery na letiště a po městě",
      "name": "Bellevue Superior Hotel Šibenik transfery",
      "description": "Soukromé taxi transfery za pevnou cenu do a z Bellevue Superior Hotel v srdci Šibeniku. Letištní transfery, meziměstské transfery a výlety do Krky, rezervované předem za cenu dohodnutou před jízdou.",
      "provider": {
        "@type": "LocalBusiness",
        "name": "Taxi Antonio",
        "telephone": "+385994471013",
        "email": "info@taxisibenik.hr",
        "address": {
          "@type": "PostalAddress",
          "addressLocality": "Šibenik",
          "addressCountry": "HR"
        },
        "aggregateRating": {
          "@type": "AggregateRating",
          "ratingValue": "4.9",
          "reviewCount": "142"
        }
      },
      "areaServed": [
        "Bellevue Superior Hotel Šibenik",
        "Šibenik"
      ],
      "url": "https://taxisibenik.hr/cs/bellevue-transfer/",
      "hasOfferCatalog": {
        "@type": "OfferCatalog",
        "name": "Pevné ceny transferů z Bellevue Superior Hotel",
        "itemListElement": [
          {
            "@type": "Offer",
            "name": "Bellevue na letiště Split",
            "price": "95",
            "priceCurrency": "EUR"
          },
          {
            "@type": "Offer",
            "name": "Bellevue na letiště Zadar",
            "price": "130",
            "priceCurrency": "EUR"
          },
          {
            "@type": "Offer",
            "name": "Bellevue na letiště Záhřeb",
            "price": "485",
            "priceCurrency": "EUR"
          },
          {
            "@type": "Offer",
            "name": "Bellevue na letiště Dubrovník",
            "price": "485",
            "priceCurrency": "EUR"
          },
          {
            "@type": "Offer",
            "name": "Bellevue do Národního parku Krka (Lozovac)",
            "price": "45",
            "priceCurrency": "EUR"
          },
          {
            "@type": "Offer",
            "name": "Bellevue do Vodic",
            "price": "30",
            "priceCurrency": "EUR"
          },
          {
            "@type": "Offer",
            "name": "Bellevue do Splitu",
            "price": "140",
            "priceCurrency": "EUR"
          },
          {
            "@type": "Offer",
            "name": "Bellevue do Zadaru",
            "price": "140",
            "priceCurrency": "EUR"
          }
        ]
      }
    },
    {
      "@context": "https://schema.org",
      "@type": "FAQPage",
      "mainEntity": [
        {
          "@type": "Question",
          "name": "Kolik stojí taxi z Bellevue Superior Hotel na letiště Split?",
          "acceptedAnswer": {
            "@type": "Answer",
            "text": "Soukromý transfer z Bellevue Superior Hotel na letiště Split stojí pevných 95 eur za vozidlo pro až 4 cestující, při rezervaci předem. Mýtné, palivo i zavazadla jsou zahrnuty a cena je stejná v obou směrech."
          }
        },
        {
          "@type": "Question",
          "name": "Kde vyzvedáváte u Bellevue Superior Hotel?",
          "acceptedAnswer": {
            "@type": "Answer",
            "text": "Přímo před hotelem. Bellevue se nachází v srdci Šibeniku a přesné místo vyzvednutí potvrdím při rezervaci, abyste nečekali u obrubníku."
          }
        },
        {
          "@type": "Question",
          "name": "Mám si transfer z Bellevue rezervovat předem?",
          "acceptedAnswer": {
            "@type": "Answer",
            "text": "Ano. Všechny uvedené ceny jsou pevné ceny pro transfery rezervované předem. Rezervace předem zaručuje vozidlo, čas vyzvednutí i cenu, což je nejdůležitější u časných letů a ve vrcholné sezoně."
          }
        },
        {
          "@type": "Question",
          "name": "Vyzvedáváte přilétající hosty na letišti?",
          "acceptedAnswer": {
            "@type": "Answer",
            "text": "Ano. U příletů sleduji váš let v reálném čase, čekám v příletové hale s cedulkou se jménem a odvezu vás rovnou do Bellevue. Čekání kvůli zpoždění letu je zdarma."
          }
        },
        {
          "@type": "Question",
          "name": "Můžete nás odvézt z Bellevue do Národního parku Krka?",
          "acceptedAnswer": {
            "@type": "Answer",
            "text": "Ano. Transfer jedním směrem ke vstupu Lozovac stojí 45 eur a ke vstupu Skradin 50 eur. Nabízím také celodenní soukromý výlet se zahrnutou dobou čekání a vyzvednutím u hotelu."
          }
        },
        {
          "@type": "Question",
          "name": "Jak transfer platím?",
          "acceptedAnswer": {
            "@type": "Answer",
            "text": "Záloha 20 % (minimálně 20 eur) potvrzuje rezervaci, bankovním převodem nebo kartou. Zbytek se platí řidiči v den jízdy, hotově nebo kartou."
          }
        }
      ]
    }
  ]
}
