{
  "slug": "taksi-pirovac-grebastica",
  "title": "Taksi Pirovac - Grebaštica | Fiksna cena €85 | TAXI Antonio",
  "description": "Taksi in zasebni prevoz, relacija Pirovac - Grebaštica. Fiksna cena €85 na vozilo, do 4 potnike, od vrat do vrat. Rezervirajte neposredno pri Antoniu.",
  "keywords": "taksi pirovac - grebaštica, prevoz pirovac - grebaštica, letališki prevoz pirovac - grebaštica",
  "og_image": "https://taxisibenik.hr/assets/img/hero-transfers.webp",
  "schema": [
    {
      "@context": "https://schema.org",
      "@type": "Service",
      "serviceType": "Zasebni taksi prevoz",
      "name": "Taksi Pirovac - Grebaštica",
      "description": "Taksi in zasebni prevoz po fiksni ceni, relacija Pirovac - Grebaštica, 85 evrov na vozilo do 4 potnike, od vrat do vrat.",
      "provider": {
        "@type": "LocalBusiness",
        "name": "Taxi Antonio",
        "telephone": "+385994471013",
        "email": "info@taxisibenik.hr",
        "address": {
          "@type": "PostalAddress",
          "addressLocality": "Šibenik",
          "addressCountry": "HR"
        },
        "aggregateRating": {
          "@type": "AggregateRating",
          "ratingValue": "4.9",
          "reviewCount": "152"
        }
      },
      "areaServed": [
        "Pirovac",
        "Grebaštica"
      ],
      "url": "https://taxisibenik.hr/sl/taksi-pirovac-grebastica/",
      "offers": {
        "@type": "Offer",
        "price": "85",
        "priceCurrency": "EUR",
        "description": "Zasebna enosmerna vožnja, relacija Pirovac - Grebaštica, na vozilo do 4 potnike. Povratno 170 evrov."
      }
    },
    {
      "@context": "https://schema.org",
      "@type": "FAQPage",
      "mainEntity": [
        {
          "@type": "Question",
          "name": "Kako dolga je relacija in koliko traja vožnja?",
          "acceptedAnswer": {
            "@type": "Answer",
            "text": "Vožnja na relaciji Pirovac - Grebaštica je približno 42 km in traja okoli 50 min pri običajnem prometu, nekoliko dlje v poletni konici. Prevzem načrtujem tako, da vas počasnejši odsek nikoli ne priganja."
          }
        },
        {
          "@type": "Question",
          "name": "Koliko stane taksi na relaciji Pirovac - Grebaštica?",
          "acceptedAnswer": {
            "@type": "Answer",
            "text": "Fiksno 85 na vozilo do 4 potnike, enosmerno, prtljaga vključena. Povratna vožnja je 170."
          }
        },
        {
          "@type": "Question",
          "name": "Kje me poberete?",
          "acceptedAnswer": {
            "@type": "Answer",
            "text": "Na vašem točnem naslovu, naj bo to hiša, hotel ali apartma. Pošljite naslov ob rezervaciji in potrdim mesto srečanja."
          }
        },
        {
          "@type": "Question",
          "name": "Kako dolgo vnaprej rezervirati?",
          "acceptedAnswer": {
            "@type": "Answer",
            "text": "Vsaj 2 uri prej, da potrdim vozilo in uro prevzema. Za hitro vožnjo pokličite ali pišite na WhatsApp."
          }
        }
      ]
    }
  ]
}