{
  "slug": "taxi-dubrovnik-aci-marina-jezera",
  "title": "Taxi Dubrovnik - ACI Marina Jezera | Prezzo fisso €530 | TAXI Antonio",
  "description": "Taxi e transfer privato, tratta Dubrovnik - ACI Marina Jezera. Prezzo fisso €530 per veicolo, fino a 4. Prenota con Antonio.",
  "keywords": "taxi dubrovnik - aci marina jezera, transfer dubrovnik - aci marina jezera, transfer aeroporto dubrovnik - aci marina jezera",
  "og_image": "https://taxisibenik.hr/assets/img/hero-transfers.webp",
  "schema": [
    {
      "@context": "https://schema.org",
      "@type": "Service",
      "serviceType": "Transfer taxi privato",
      "name": "Taxi Dubrovnik - ACI Marina Jezera",
      "description": "Taxi e transfer privato a prezzo fisso, tratta Dubrovnik - ACI Marina Jezera, 530 euro per veicolo fino a 4 passeggeri, porta a porta.",
      "provider": {
        "@type": "LocalBusiness",
        "name": "Taxi Antonio",
        "telephone": "+385994471013",
        "email": "info@taxisibenik.hr",
        "address": {
          "@type": "PostalAddress",
          "addressLocality": "Šibenik",
          "addressCountry": "HR"
        },
        "aggregateRating": {
          "@type": "AggregateRating",
          "ratingValue": "4.9",
          "reviewCount": "142"
        }
      },
      "areaServed": [
        "Dubrovnik",
        "ACI Marina Jezera"
      ],
      "url": "https://taxisibenik.hr/it/taxi-dubrovnik-aci-marina-jezera/",
      "offers": {
        "@type": "Offer",
        "price": "530",
        "priceCurrency": "EUR",
        "description": "Corsa privata di sola andata, tratta Dubrovnik - ACI Marina Jezera, per veicolo fino a 4 passeggeri. Andata e ritorno 1060 euro."
      }
    },
    {
      "@context": "https://schema.org",
      "@type": "FAQPage",
      "mainEntity": [
        {
          "@type": "Question",
          "name": "Quanto costa un transfer da Dubrovnik a ACI Marina Jezera?",
          "acceptedAnswer": {
            "@type": "Answer",
            "text": "Fisso 530 per veicolo, fino a 4 passeggeri, solo andata, con pedaggi, carburante e bagagli inclusi. Andata e ritorno 1060."
          }
        },
        {
          "@type": "Question",
          "name": "Può venirmi a prendere direttamente alla marina?",
          "acceptedAnswer": {
            "@type": "Answer",
            "text": "Sì. La incontro all'ingresso della marina o alla reception e L'aiuto con i bagagli, così passa direttamente dal pontile al veicolo."
          }
        },
        {
          "@type": "Question",
          "name": "Può adattare il transfer agli orari della mia barca?",
          "acceptedAnswer": {
            "@type": "Answer",
            "text": "Sì. Mi invii l'orario del charter, del check-in o della partenza al momento della prenotazione e pianifico il ritiro di conseguenza."
          }
        },
        {
          "@type": "Question",
          "name": "Con quanto anticipo devo prenotare?",
          "acceptedAnswer": {
            "@type": "Answer",
            "text": "Almeno 2 ore prima, così confermo il veicolo e l'orario di ritiro. Per una corsa prima, mi chiami o mi scriva su WhatsApp."
          }
        }
      ]
    }
  ]
}