{
  "slug": "taxi-rogoznica-zadar-lentoasema",
  "title": "Taksi Rogoznica - Zadarin lentoasema | Kiinteä hinta €160 | TAXI Antonio",
  "description": "Yksityinen taksi ja kuljetus, reitti Rogoznica - Zadarin lentoasema. Kiinteä hinta €160 per auto, enintään 4. Varaa suoraan Antoniolta.",
  "keywords": "taksi rogoznica - zadarin lentoasema, kuljetus rogoznica - zadarin lentoasema, lentokenttäkuljetus rogoznica - zadarin lentoasema",
  "og_image": "https://taxisibenik.hr/assets/img/hero-transfers.webp",
  "schema": [
    {
      "@context": "https://schema.org",
      "@type": "Service",
      "serviceType": "Yksityinen taksikuljetus",
      "name": "Taksi Rogoznica - Zadarin lentoasema",
      "description": "Yksityinen taksi ja kuljetus kiinteään hintaan, reitti Rogoznica - Zadarin lentoasema, 160 euroa per auto enintään 4 matkustajalle, ovelta ovelle.",
      "provider": {
        "@type": "LocalBusiness",
        "name": "Taxi Antonio",
        "telephone": "+385994471013",
        "email": "info@taxisibenik.hr",
        "address": {
          "@type": "PostalAddress",
          "addressLocality": "Šibenik",
          "addressCountry": "HR"
        },
        "aggregateRating": {
          "@type": "AggregateRating",
          "ratingValue": "4.9",
          "reviewCount": "152"
        }
      },
      "areaServed": [
        "Rogoznica",
        "Zadarin lentoasema"
      ],
      "url": "https://taxisibenik.hr/fi/taxi-rogoznica-zadar-lentoasema/",
      "offers": {
        "@type": "Offer",
        "price": "160",
        "priceCurrency": "EUR",
        "description": "Yhdensuuntainen yksityinen matka, reitti Rogoznica - Zadarin lentoasema, per auto enintään 4 matkustajalle. Meno ja paluu 320 euroa."
      }
    },
    {
      "@context": "https://schema.org",
      "@type": "FAQPage",
      "mainEntity": [
        {
          "@type": "Question",
          "name": "Kuinka pitkä reitti on ja kuinka kauan matka kestää?",
          "acceptedAnswer": {
            "@type": "Answer",
            "text": "Matka reitillä Rogoznica - Zadarin lentoasema on noin 107 km ja kestää noin 1 h 40 min normaalissa liikenteessä, kesän huippukaudella hieman kauemmin. Suunnittelen noudon niin, ettei hidas matka koskaan aiheuta kiirettä."
          }
        },
        {
          "@type": "Question",
          "name": "Paljonko taksi maksaa reitillä Rogoznica - Zadarin lentoasema?",
          "acceptedAnswer": {
            "@type": "Answer",
            "text": "Kiinteä 160 per auto, yhdensuuntainen matka, enintään 4 matkustajalle. Hinta on per auto, ei per henkilö, ja sisältää tietullit, polttoaineen ja matkatavarat. Meno-paluumatka maksaa 320."
          }
        },
        {
          "@type": "Question",
          "name": "Milloin minun pitäisi lähteä lentoasemalle?",
          "acceptedAnswer": {
            "@type": "Answer",
            "text": "Yleensä noin 3 tuntia ennen kansainvälistä ja 2 tuntia ennen kotimaista lentoa. Kerro lentoaikasi, niin vahvistan tarkan noutoajan."
          }
        },
        {
          "@type": "Question",
          "name": "Ajatteko lähtöterminaaliin asti?",
          "acceptedAnswer": {
            "@type": "Answer",
            "text": "Kyllä. Vien sinut suoraan lähtöterminaaliin ja autan matkatavaroiden kanssa. Ei kävelyä parkkipaikalta eikä bussikuljetusta."
          }
        },
        {
          "@type": "Question",
          "name": "Kuinka paljon etukäteen minun pitäisi varata?",
          "acceptedAnswer": {
            "@type": "Answer",
            "text": "Vähintään 2 tuntia aiemmin, jotta voin vahvistaa auton ja noudon, ja aikaisemmin varhaisia lentoja ja huippukautta varten. Lyhyellä varoitusajalla soita tai kirjoita minulle WhatsAppissa."
          }
        }
      ]
    }
  ]
}