{
  "slug": "taxi-letiste-zagreb-marina-kremik",
  "title": "Taxi Letiště Zagreb - Marina Kremik | Pevná cena €500 | TAXI Antonio",
  "description": "Taxi a soukromý transfer, trasa Letiště Zagreb - Marina Kremik. Pevná cena €500 za vozidlo, až 4. Rezervujte u Antonia.",
  "keywords": "taxi letiště zagreb - marina kremik, transfer letiště zagreb - marina kremik, letištní transfer letiště zagreb - marina kremik",
  "og_image": "https://taxisibenik.hr/assets/img/hero-transfers.webp",
  "schema": [
    {
      "@context": "https://schema.org",
      "@type": "Service",
      "serviceType": "Soukromý taxi transfer",
      "name": "Taxi Letiště Zagreb - Marina Kremik",
      "description": "Taxi a soukromý transfer za pevnou cenu, trasa Letiště Zagreb - Marina Kremik, 500 eur za vozidlo až pro 4 cestující, ode dveří ke dveřím.",
      "provider": {
        "@type": "LocalBusiness",
        "name": "Taxi Antonio",
        "telephone": "+385994471013",
        "email": "info@taxisibenik.hr",
        "address": {
          "@type": "PostalAddress",
          "addressLocality": "Šibenik",
          "addressCountry": "HR"
        },
        "aggregateRating": {
          "@type": "AggregateRating",
          "ratingValue": "4.9",
          "reviewCount": "142"
        }
      },
      "areaServed": [
        "Letiště Zagreb",
        "Marina Kremik"
      ],
      "url": "https://taxisibenik.hr/cs/taxi-letiste-zagreb-marina-kremik/",
      "offers": {
        "@type": "Offer",
        "price": "500",
        "priceCurrency": "EUR",
        "description": "Soukromá jednosměrná jízda, trasa Letiště Zagreb - Marina Kremik, za vozidlo až pro 4 cestující. Zpáteční 1000 eur."
      }
    },
    {
      "@context": "https://schema.org",
      "@type": "FAQPage",
      "mainEntity": [
        {
          "@type": "Question",
          "name": "Kde mě přivítáte?",
          "acceptedAnswer": {
            "@type": "Answer",
            "text": "V příletové hale, hned za výdejem zavazadel, s cedulkou s vaším jménem. Pomůžu se zavazadly a doprovodím vás k vozidlu."
          }
        },
        {
          "@type": "Question",
          "name": "Co když má můj let zpoždění?",
          "acceptedAnswer": {
            "@type": "Answer",
            "text": "Žádný problém. Váš let sleduji v reálném čase a přizpůsobím vyzvednutí skutečnému přistání, bez příplatku za čekání."
          }
        },
        {
          "@type": "Question",
          "name": "Vyzvednete mě i u terminálu pro soukromé letectví?",
          "acceptedAnswer": {
            "@type": "Answer",
            "text": "Ano. Vítám cestující jak u komerčního terminálu, tak u terminálu pro soukromé a všeobecné letectví, který slouží soukromým tryskáčům a charterům. Při rezervaci mi jen řekněte svůj terminál nebo FBO."
          }
        },
        {
          "@type": "Question",
          "name": "Kolik stojí transfer na trase Letiště Zagreb - Marina Kremik?",
          "acceptedAnswer": {
            "@type": "Answer",
            "text": "Pevně 500 za vozidlo až pro 4 cestující, jednosměrná, mýtné a zavazadla v ceně. Zpáteční jízda je 1000."
          }
        },
        {
          "@type": "Question",
          "name": "S jakým předstihem rezervovat?",
          "acceptedAnswer": {
            "@type": "Answer",
            "text": "Alespoň 2 hodiny předem, abych naplánoval podle vašeho letu. Pro vyzvednutí týž den po náhlé změně zavolejte nebo napište na WhatsApp."
          }
        }
      ]
    }
  ]
}